aporthq_middleware_fastapi/__init__.py
aporthq_middleware_fastapi/middleware.py
aporthq_middleware_fastapi/types.py
aporthq_middleware_fastapi/validation.py
aporthq_middleware_fastapi-0.1.0.dist-info/licenses/LICENSE
aporthq_middleware_fastapi-0.1.0.dist-info/METADATA
aporthq_middleware_fastapi-0.1.0.dist-info/WHEEL
aporthq_middleware_fastapi-0.1.0.dist-info/top_level.txt
aporthq_middleware_fastapi-0.1.0.dist-info/RECORD
